python_redis_orm/__init__.py
python_redis_orm/core.py
python_redis_orm/tests/full_test.py
python_redis_orm/utils.py
python_redis_orm-0.5.4.dist-info/LICENSE
python_redis_orm-0.5.4.dist-info/WHEEL
python_redis_orm-0.5.4.dist-info/METADATA
python_redis_orm-0.5.4.dist-info/RECORD
