Metadata-Version: 2.1
Name: python-redis-orm
Version: 0.5.4
Summary: Python Redis ORM library that gives redis easy-to-use objects with fields and speeds a development up, inspired by Django ORM
Home-page: https://github.com/gh0st-work/python_redis_orm
License: MIT
Keywords: python,redis,ORM,django,database
Author: Anton Nechaev
Author-email: antonnechaev990@gmail.com
Requires-Python: >=3.6,<4.0
Classifier: Development Status :: 5 - Production/Stable
Classifier: Environment :: Web Environment
Classifier: Framework :: Django
Classifier: Framework :: Django :: 3.0
Classifier: Intended Audience :: Developers
Classifier: License :: OSI Approved :: MIT License
Classifier: Operating System :: OS Independent
Classifier: Programming Language :: Python
Classifier: Programming Language :: Python :: 3
Classifier: Programming Language :: Python :: 3 :: Only
Classifier: Programming Language :: Python :: 3.6
Classifier: Programming Language :: Python :: 3.7
Classifier: Programming Language :: Python :: 3.8
Classifier: Programming Language :: Python :: 3.9
Classifier: Topic :: Database :: Front-Ends
Classifier: Topic :: Internet :: WWW/HTTP :: Dynamic Content
Classifier: Topic :: Software Development
Classifier: Topic :: Software Development :: Libraries
Classifier: Topic :: Software Development :: Libraries :: Python Modules
Classifier: Topic :: Software Development :: Object Brokering
Classifier: Topic :: Utilities
Requires-Dist: pytz (>=2021,<2022)
Requires-Dist: redis (>=3.5.3,<4.0.0)
Project-URL: Repository, https://github.com/gh0st-work/python_redis_orm
